aifig/__init__.py
aifig/draw.py
aifig/element.py
aifig/figure.py
aifig/graph.py
aifig-0.1.7.dist-info/LICENSE
aifig-0.1.7.dist-info/METADATA
aifig-0.1.7.dist-info/WHEEL
aifig-0.1.7.dist-info/top_level.txt
aifig-0.1.7.dist-info/RECORD
