Metadata-Version: 2.1
Name: aifig
Version: 0.1.7
Summary: A machine learning figure generation library
Home-page: https://github.com/evgiz/aifig
Author: Sigve Rokenes
Author-email: me@evgiz.net
License: UNKNOWN
Platform: UNKNOWN
Classifier: Programming Language :: Python :: 3
Classifier: License :: OSI Approved :: MIT License
Classifier: Operating System :: OS Independent
Requires-Dist: svgwrite
